friskby_controlpanel/__init__.py
friskby_controlpanel/ctljson.py
friskby_controlpanel/forms.py
friskby_controlpanel/friskby_controlpanel.py
friskby_controlpanel/friskby_interface.py
friskby_controlpanel/friskby_settings.py
friskby_controlpanel/static/css/pure-base-min.css
friskby_controlpanel/static/css/pure-buttons-min.css
friskby_controlpanel/static/css/pure-forms-min.css
friskby_controlpanel/static/css/pure-tables-min.css
friskby_controlpanel/static/css/style.css
friskby_controlpanel/static/fonts/Palanquin-ExtraLight.ttf
friskby_controlpanel/static/fonts/Palanquin-Medium.ttf
friskby_controlpanel/static/fonts/Palanquin-Regular.ttf
friskby_controlpanel/static/fonts/Palanquin-SemiBold.ttf
friskby_controlpanel/static/img/friskby-logo.png
friskby_controlpanel/static/js/ui.js
friskby_controlpanel/templates/base.html
friskby_controlpanel/templates/dashboard.html
friskby_controlpanel/templates/register.html
friskby_controlpanel/templates/registered.html
friskby_controlpanel/templates/service.html
friskby_controlpanel/templates/settings.html
friskby_controlpanel-0.8.4.data/data/bin/fby_init
friskby_controlpanel-0.8.4.dist-info/top_level.txt
friskby_controlpanel-0.8.4.dist-info/METADATA
friskby_controlpanel-0.8.4.dist-info/DESCRIPTION.rst
friskby_controlpanel-0.8.4.dist-info/metadata.json
friskby_controlpanel-0.8.4.dist-info/WHEEL
friskby_controlpanel-0.8.4.dist-info/RECORD
