Metadata-Version: 2.0
Name: friskby-controlpanel
Version: 0.8.4
Summary: Friskby device control panel
Home-page: https://github.com/FriskByBergen/python-friskby-controlpanel
Author: FriskBy Bergen
Author-email: jonas@drange.net
License: GNU General Public License, Version 3
Keywords: friskby bergen frisk by rpiparticle a-small-code
Platform: UNKNOWN
Classifier: Development Status :: 3 - Alpha
Classifier: Intended Audience :: Developers
Classifier: License :: OSI Approved :: GNU General Public License v3 or later (GPLv3+)
Classifier: Programming Language :: Python :: 2
Classifier: Programming Language :: Python :: 3
Provides: friskby_controlpanel
Requires-Dist: friskby (>=0.72.1)
Requires-Dist: flask
Requires-Dist: rpiparticle (>=0.9.2)
Requires-Dist: Flask-WTF
